MANIFEST.in
README
setup.py
classic/__init__.py
classic/admin.py
classic/make.py
classic/models.py
classic/urls.py
classic/templates/classic/media/css/base.css
classic/templates/classic/media/css/style.css
classic/templates/classic/media/css/tinymce.css
classic/templates/classic/media/img/logo.png
classic/templates/classic/media/img/splash.jpg
classic/templates/classic/templates/base_template.html
redsolutioncms.template_classic.egg-info/PKG-INFO
redsolutioncms.template_classic.egg-info/SOURCES.txt
redsolutioncms.template_classic.egg-info/dependency_links.txt
redsolutioncms.template_classic.egg-info/entry_points.txt
redsolutioncms.template_classic.egg-info/not-zip-safe
redsolutioncms.template_classic.egg-info/top_level.txt