Metadata-Version: 1.0
Name: redsolutioncms.template-classic
Version: 0.1.0
Summary: Default template fot RedsoultionCMS
Home-page: http://packages.python.org/redsolution-template-classic
Author: Alexey Kuligin
Author-email: alexey.kuligin@redsolution.ru
License: cc by
Keywords: redsoutioncms template
Platform: UNKNOWN
Classifier: Development Status :: 3 - Alpha
Classifier: Intended Audience :: Developers
Classifier: License :: Freely Distributable
Classifier: Framework :: Django
Classifier: Environment :: Web Environment
Classifier: Natural Language :: Russian
Classifier: Natural Language :: English
Classifier: Operating System :: OS Independent
Classifier: Programming Language :: Python
Classifier: Topic :: Internet :: WWW/HTTP :: Site Management
